MANIFEST.in
README.rst
setup.py
cciaa/__init__.py
cciaa.modulistica.egg-info/PKG-INFO
cciaa.modulistica.egg-info/SOURCES.txt
cciaa.modulistica.egg-info/dependency_links.txt
cciaa.modulistica.egg-info/entry_points.txt
cciaa.modulistica.egg-info/namespace_packages.txt
cciaa.modulistica.egg-info/not-zip-safe
cciaa.modulistica.egg-info/requires.txt
cciaa.modulistica.egg-info/top_level.txt
cciaa/modulistica/__init__.py
cciaa/modulistica/configure.zcml
cciaa/modulistica/extender.py
cciaa/modulistica/interfaces.py
cciaa/modulistica/behaviors/__init__.py
cciaa/modulistica/behaviors/adapter.py
cciaa/modulistica/behaviors/configure.zcml
cciaa/modulistica/behaviors/folder_modulistica.py
cciaa/modulistica/browser/__init__.py
cciaa/modulistica/browser/cciaa_modulistica_view.pt
cciaa/modulistica/browser/configure.zcml
cciaa/modulistica/browser/modulistica.py
cciaa/modulistica/browser/images/globe.png
cciaa/modulistica/browser/stylesheets/cciaa.modulistica.css
cciaa/modulistica/locales/cciaa.modulistica-manual.pot
cciaa/modulistica/locales/cciaa.modulistica.pot
cciaa/modulistica/locales/i18n.sh
cciaa/modulistica/locales/it/LC_MESSAGES/cciaa.modulistica.po
cciaa/modulistica/profiles/default/browserlayer.xml
cciaa/modulistica/profiles/default/catalog.xml
cciaa/modulistica/profiles/default/cssregistry.xml
cciaa/modulistica/profiles/default/metadata.xml
cciaa/modulistica/profiles/default/types.xml
cciaa/modulistica/profiles/default/types/Folder.xml
cciaa/modulistica/tests/__init__.py
cciaa/modulistica/tests/base.py
cciaa/modulistica/tests/test_view.py
docs/HISTORY.txt
docs/LICENSE.GPL
docs/LICENSE.txt